integron_finder/__init__.py
integron_finder/annotation.py
integron_finder/argparse_utils.py
integron_finder/attc.py
integron_finder/config.py
integron_finder/hmm.py
integron_finder/infernal.py
integron_finder/integrase.py
integron_finder/integron.py
integron_finder/prot_db.py
integron_finder/results.py
integron_finder/topology.py
integron_finder/utils.py
integron_finder/data/Functional_annotation/NCBIfam-AMRFinder.hmm
integron_finder/data/Models/IntI.hmm
integron_finder/data/Models/attc_4.cm
integron_finder/data/Models/integron_integrase.hmm
integron_finder/data/Models/phage-int.hmm
integron_finder/data/Models/variants_Pc_intI1.fst
integron_finder/scripts/__init__.py
integron_finder/scripts/finder.py
integron_finder/scripts/merge.py
integron_finder/scripts/split.py
integron_finder-2.0rc10.data/data/share/integron_finder/doc/html/.buildinfo
integron_finder-2.0rc10.data/data/share/integron_finder/doc/html/genindex.html
integron_finder-2.0rc10.data/data/share/integron_finder/doc/html/index.html
integron_finder-2.0rc10.data/data/share/integron_finder/doc/html/objects.inv
integron_finder-2.0rc10.data/data/share/integron_finder/doc/html/py-modindex.html
integron_finder-2.0rc10.data/data/share/integron_finder/doc/html/search.html
integron_finder-2.0rc10.data/data/share/integron_finder/doc/html/searchindex.js
integron_finder-2.0rc10.data/data/share/integron_finder/doc/html/_images/benchmark.png
integron_finder-2.0rc10.data/data/share/integron_finder/doc/html/_images/evalue_attC.png
integron_finder-2.0rc10.data/data/share/integron_finder/doc/html/_images/pipeline.png
integron_finder-2.0rc10.data/data/share/integron_finder/doc/html/_images/schema.png
integron_finder-2.0rc10.data/data/share/integron_finder/doc/html/_modules/collections.html
integron_finder-2.0rc10.data/data/share/integron_finder/doc/html/_modules/index.html
integron_finder-2.0rc10.data/data/share/integron_finder/doc/html/_modules/logging.html
integron_finder-2.0rc10.dist-info/COPYING
integron_finder-2.0rc10.dist-info/METADATA
integron_finder-2.0rc10.dist-info/WHEEL
integron_finder-2.0rc10.dist-info/entry_points.txt
integron_finder-2.0rc10.dist-info/top_level.txt
integron_finder-2.0rc10.dist-info/RECORD
