Metadata-Version: 2.1
Name: integron-finder
Version: 2.0rc10
Summary: Integron Finder aims at detecting integrons in DNA sequences
Home-page: https://github.com/gem-pasteur/Integron_Finder/
Author: Jean Cury
Author-email: jean.cury@normalesup.org
License: GPLv3
Project-URL: Bug Tracker, https://github.com/pypa/sampleproject/issues
Project-URL: Documentation, https://integronfinder.readthedocs.io/en/latest/
Platform: UNKNOWN
Classifier: Programming Language :: Python :: 3
Classifier: Programming Language :: Python :: 3.7
Classifier: Programming Language :: Python :: 3.8
Classifier: Programming Language :: Python :: 3.9
Classifier: License :: OSI Approved :: GNU General Public License v3 (GPLv3)
Classifier: Operating System :: POSIX
Classifier: Intended Audience :: Science/Research
Classifier: Topic :: Scientific/Engineering :: Bio-Informatics
Requires-Python: >=3.7
License-File: COPYING
Requires-Dist: numpy (>=1.19)
Requires-Dist: matplotlib (>=3.2)
Requires-Dist: pandas (>=1.1)
Requires-Dist: biopython (>=1.78)
Requires-Dist: colorlog
Provides-Extra: dev
Requires-Dist: sphinx ; extra == 'dev'
Requires-Dist: sphinx-rtd-theme ; extra == 'dev'
Requires-Dist: coverage ; extra == 'dev'
Requires-Dist: build ; extra == 'dev'
